{ "protocolVersion": { "major": 8, "minor": 0 }, "decentralization": 0, "extraPraosEntropy": null, "maxBlockHeaderSize": 1100, "maxBlockBodySize": 90112, "maxTxSize": 16384, "txFeeFixed": 44, "txFeePerByte": 155381, "minUTxOValue": 0, "stakeAddressDeposit": 2000000, "stakePoolDeposit": 500000000, "minPoolCost": 170000000, "poolRetireMaxEpoch": 18, "stakePoolTargetNum": 500, "poolPledgeInfluence": 0.3, "monetaryExpansion": 0.003, "treasuryCut": 0.2, "costModels": { "unCostModels": "156" }, "executionUnitPrices": { "priceMemory": 0.0577, "priceSteps": 7.21e-05 }, "maxTxExecutionUnits": { "steps": 10000000000, "memory": 14000000 }, "maxBlockExecutionUnits": { "steps": 62000000, "memory": 20000000000 }, "maxValueSize": 5000, "collateralPercentage": 150, "maxCollateralInputs": 3, "utxoCostPerByte": 4310 }
